{
    "description": "",
    "tags": [],
    "size": {
        "height": 750,
        "width": 750
    },
    "objects": [
        {
            "id": 98185763,
            "classId": 6509559,
            "description": "",
            "geometryType": "rectangle",
            "labelerLogin": "inbox@datasetninja.com",
            "createdAt": "2023-12-15T16:15:18.735Z",
            "updatedAt": "2023-12-15T16:15:18.735Z",
            "tags": [],
            "classTitle": "plasmodium",
            "points": {
                "exterior": [
                    [
                        497,
                        396
                    ],
                    [
                        537,
                        436
                    ]
                ],
                "interior": []
            }
        },
        {
            "id": 98185762,
            "classId": 6509559,
            "description": "",
            "geometryType": "rectangle",
            "labelerLogin": "inbox@datasetninja.com",
            "createdAt": "2023-12-15T16:15:18.735Z",
            "updatedAt": "2023-12-15T16:15:18.735Z",
            "tags": [],
            "classTitle": "plasmodium",
            "points": {
                "exterior": [
                    [
                        412,
                        503
                    ],
                    [
                        452,
                        543
                    ]
                ],
                "interior": []
            }
        },
        {
            "id": 98185761,
            "classId": 6509559,
            "description": "",
            "geometryType": "rectangle",
            "labelerLogin": "inbox@datasetninja.com",
            "createdAt": "2023-12-15T16:15:18.734Z",
            "updatedAt": "2023-12-15T16:15:18.734Z",
            "tags": [],
            "classTitle": "plasmodium",
            "points": {
                "exterior": [
                    [
                        588,
                        520
                    ],
                    [
                        628,
                        560
                    ]
                ],
                "interior": []
            }
        },
        {
            "id": 98185760,
            "classId": 6509559,
            "description": "",
            "geometryType": "rectangle",
            "labelerLogin": "inbox@datasetninja.com",
            "createdAt": "2023-12-15T16:15:18.734Z",
            "updatedAt": "2023-12-15T16:15:18.734Z",
            "tags": [],
            "classTitle": "plasmodium",
            "points": {
                "exterior": [
                    [
                        681,
                        579
                    ],
                    [
                        721,
                        619
                    ]
                ],
                "interior": []
            }
        },
        {
            "id": 98185759,
            "classId": 6509559,
            "description": "",
            "geometryType": "rectangle",
            "labelerLogin": "inbox@datasetninja.com",
            "createdAt": "2023-12-15T16:15:18.734Z",
            "updatedAt": "2023-12-15T16:15:18.734Z",
            "tags": [],
            "classTitle": "plasmodium",
            "points": {
                "exterior": [
                    [
                        684,
                        699
                    ],
                    [
                        724,
                        739
                    ]
                ],
                "interior": []
            }
        },
        {
            "id": 98185758,
            "classId": 6509559,
            "description": "",
            "geometryType": "rectangle",
            "labelerLogin": "inbox@datasetninja.com",
            "createdAt": "2023-12-15T16:15:18.733Z",
            "updatedAt": "2023-12-15T16:15:18.733Z",
            "tags": [],
            "classTitle": "plasmodium",
            "points": {
                "exterior": [
                    [
                        60,
                        615
                    ],
                    [
                        100,
                        655
                    ]
                ],
                "interior": []
            }
        },
        {
            "id": 98185757,
            "classId": 6509559,
            "description": "",
            "geometryType": "rectangle",
            "labelerLogin": "inbox@datasetninja.com",
            "createdAt": "2023-12-15T16:15:18.732Z",
            "updatedAt": "2023-12-15T16:15:18.732Z",
            "tags": [],
            "classTitle": "plasmodium",
            "points": {
                "exterior": [
                    [
                        473,
                        186
                    ],
                    [
                        513,
                        226
                    ]
                ],
                "interior": []
            }
        },
        {
            "id": 98185756,
            "classId": 6509559,
            "description": "",
            "geometryType": "rectangle",
            "labelerLogin": "inbox@datasetninja.com",
            "createdAt": "2023-12-15T16:15:18.731Z",
            "updatedAt": "2023-12-15T16:15:18.731Z",
            "tags": [],
            "classTitle": "plasmodium",
            "points": {
                "exterior": [
                    [
                        478,
                        116
                    ],
                    [
                        518,
                        156
                    ]
                ],
                "interior": []
            }
        },
        {
            "id": 98185755,
            "classId": 6509559,
            "description": "",
            "geometryType": "rectangle",
            "labelerLogin": "inbox@datasetninja.com",
            "createdAt": "2023-12-15T16:15:18.730Z",
            "updatedAt": "2023-12-15T16:15:18.730Z",
            "tags": [],
            "classTitle": "plasmodium",
            "points": {
                "exterior": [
                    [
                        498,
                        81
                    ],
                    [
                        538,
                        121
                    ]
                ],
                "interior": []
            }
        },
        {
            "id": 98185754,
            "classId": 6509559,
            "description": "",
            "geometryType": "rectangle",
            "labelerLogin": "inbox@datasetninja.com",
            "createdAt": "2023-12-15T16:15:18.730Z",
            "updatedAt": "2023-12-15T16:15:18.730Z",
            "tags": [],
            "classTitle": "plasmodium",
            "points": {
                "exterior": [
                    [
                        445,
                        571
                    ],
                    [
                        485,
                        611
                    ]
                ],
                "interior": []
            }
        },
        {
            "id": 98185753,
            "classId": 6509559,
            "description": "",
            "geometryType": "rectangle",
            "labelerLogin": "inbox@datasetninja.com",
            "createdAt": "2023-12-15T16:15:18.730Z",
            "updatedAt": "2023-12-15T16:15:18.730Z",
            "tags": [],
            "classTitle": "plasmodium",
            "points": {
                "exterior": [
                    [
                        426,
                        42
                    ],
                    [
                        466,
                        82
                    ]
                ],
                "interior": []
            }
        },
        {
            "id": 98185752,
            "classId": 6509559,
            "description": "",
            "geometryType": "rectangle",
            "labelerLogin": "inbox@datasetninja.com",
            "createdAt": "2023-12-15T16:15:18.729Z",
            "updatedAt": "2023-12-15T16:15:18.729Z",
            "tags": [],
            "classTitle": "plasmodium",
            "points": {
                "exterior": [
                    [
                        582,
                        354
                    ],
                    [
                        622,
                        394
                    ]
                ],
                "interior": []
            }
        },
        {
            "id": 98185751,
            "classId": 6509559,
            "description": "",
            "geometryType": "rectangle",
            "labelerLogin": "inbox@datasetninja.com",
            "createdAt": "2023-12-15T16:15:18.729Z",
            "updatedAt": "2023-12-15T16:15:18.729Z",
            "tags": [],
            "classTitle": "plasmodium",
            "points": {
                "exterior": [
                    [
                        210,
                        640
                    ],
                    [
                        250,
                        680
                    ]
                ],
                "interior": []
            }
        },
        {
            "id": 98185750,
            "classId": 6509559,
            "description": "",
            "geometryType": "rectangle",
            "labelerLogin": "inbox@datasetninja.com",
            "createdAt": "2023-12-15T16:15:18.728Z",
            "updatedAt": "2023-12-15T16:15:18.728Z",
            "tags": [],
            "classTitle": "plasmodium",
            "points": {
                "exterior": [
                    [
                        55,
                        204
                    ],
                    [
                        95,
                        244
                    ]
                ],
                "interior": []
            }
        },
        {
            "id": 98185749,
            "classId": 6509559,
            "description": "",
            "geometryType": "rectangle",
            "labelerLogin": "inbox@datasetninja.com",
            "createdAt": "2023-12-15T16:15:18.728Z",
            "updatedAt": "2023-12-15T16:15:18.728Z",
            "tags": [],
            "classTitle": "plasmodium",
            "points": {
                "exterior": [
                    [
                        234,
                        21
                    ],
                    [
                        274,
                        61
                    ]
                ],
                "interior": []
            }
        },
        {
            "id": 98185748,
            "classId": 6509559,
            "description": "",
            "geometryType": "rectangle",
            "labelerLogin": "inbox@datasetninja.com",
            "createdAt": "2023-12-15T16:15:18.727Z",
            "updatedAt": "2023-12-15T16:15:18.727Z",
            "tags": [],
            "classTitle": "plasmodium",
            "points": {
                "exterior": [
                    [
                        237,
                        165
                    ],
                    [
                        277,
                        205
                    ]
                ],
                "interior": []
            }
        },
        {
            "id": 98185747,
            "classId": 6509559,
            "description": "",
            "geometryType": "rectangle",
            "labelerLogin": "inbox@datasetninja.com",
            "createdAt": "2023-12-15T16:15:18.727Z",
            "updatedAt": "2023-12-15T16:15:18.727Z",
            "tags": [],
            "classTitle": "plasmodium",
            "points": {
                "exterior": [
                    [
                        424,
                        341
                    ],
                    [
                        464,
                        381
                    ]
                ],
                "interior": []
            }
        }
    ]
}