{
    "description": "",
    "tags": [],
    "size": {
        "height": 768,
        "width": 1024
    },
    "objects": [
        {
            "id": 98178377,
            "classId": 6509560,
            "description": "",
            "geometryType": "rectangle",
            "labelerLogin": "inbox@datasetninja.com",
            "createdAt": "2023-12-15T16:14:08.549Z",
            "updatedAt": "2023-12-15T16:14:08.549Z",
            "tags": [],
            "classTitle": "trophozoite",
            "points": {
                "exterior": [
                    [
                        0,
                        258
                    ],
                    [
                        47,
                        308
                    ]
                ],
                "interior": []
            }
        },
        {
            "id": 98178376,
            "classId": 6509560,
            "description": "",
            "geometryType": "rectangle",
            "labelerLogin": "inbox@datasetninja.com",
            "createdAt": "2023-12-15T16:14:08.548Z",
            "updatedAt": "2023-12-15T16:14:08.548Z",
            "tags": [],
            "classTitle": "trophozoite",
            "points": {
                "exterior": [
                    [
                        247,
                        247
                    ],
                    [
                        297,
                        297
                    ]
                ],
                "interior": []
            }
        },
        {
            "id": 98178375,
            "classId": 6509560,
            "description": "",
            "geometryType": "rectangle",
            "labelerLogin": "inbox@datasetninja.com",
            "createdAt": "2023-12-15T16:14:08.548Z",
            "updatedAt": "2023-12-15T16:14:08.548Z",
            "tags": [],
            "classTitle": "trophozoite",
            "points": {
                "exterior": [
                    [
                        451,
                        167
                    ],
                    [
                        501,
                        217
                    ]
                ],
                "interior": []
            }
        },
        {
            "id": 98178374,
            "classId": 6509560,
            "description": "",
            "geometryType": "rectangle",
            "labelerLogin": "inbox@datasetninja.com",
            "createdAt": "2023-12-15T16:14:08.548Z",
            "updatedAt": "2023-12-15T16:14:08.548Z",
            "tags": [],
            "classTitle": "trophozoite",
            "points": {
                "exterior": [
                    [
                        591,
                        29
                    ],
                    [
                        641,
                        79
                    ]
                ],
                "interior": []
            }
        },
        {
            "id": 98178373,
            "classId": 6509560,
            "description": "",
            "geometryType": "rectangle",
            "labelerLogin": "inbox@datasetninja.com",
            "createdAt": "2023-12-15T16:14:08.548Z",
            "updatedAt": "2023-12-15T16:14:08.548Z",
            "tags": [],
            "classTitle": "trophozoite",
            "points": {
                "exterior": [
                    [
                        542,
                        0
                    ],
                    [
                        592,
                        43
                    ]
                ],
                "interior": []
            }
        },
        {
            "id": 98178372,
            "classId": 6509560,
            "description": "",
            "geometryType": "rectangle",
            "labelerLogin": "inbox@datasetninja.com",
            "createdAt": "2023-12-15T16:14:08.548Z",
            "updatedAt": "2023-12-15T16:14:08.548Z",
            "tags": [],
            "classTitle": "trophozoite",
            "points": {
                "exterior": [
                    [
                        349,
                        0
                    ],
                    [
                        399,
                        44
                    ]
                ],
                "interior": []
            }
        },
        {
            "id": 98178371,
            "classId": 6509560,
            "description": "",
            "geometryType": "rectangle",
            "labelerLogin": "inbox@datasetninja.com",
            "createdAt": "2023-12-15T16:14:08.547Z",
            "updatedAt": "2023-12-15T16:14:08.547Z",
            "tags": [],
            "classTitle": "trophozoite",
            "points": {
                "exterior": [
                    [
                        175,
                        394
                    ],
                    [
                        225,
                        444
                    ]
                ],
                "interior": []
            }
        },
        {
            "id": 98178370,
            "classId": 6509560,
            "description": "",
            "geometryType": "rectangle",
            "labelerLogin": "inbox@datasetninja.com",
            "createdAt": "2023-12-15T16:14:08.547Z",
            "updatedAt": "2023-12-15T16:14:08.547Z",
            "tags": [],
            "classTitle": "trophozoite",
            "points": {
                "exterior": [
                    [
                        176,
                        460
                    ],
                    [
                        226,
                        510
                    ]
                ],
                "interior": []
            }
        },
        {
            "id": 98178369,
            "classId": 6509560,
            "description": "",
            "geometryType": "rectangle",
            "labelerLogin": "inbox@datasetninja.com",
            "createdAt": "2023-12-15T16:14:08.547Z",
            "updatedAt": "2023-12-15T16:14:08.547Z",
            "tags": [],
            "classTitle": "trophozoite",
            "points": {
                "exterior": [
                    [
                        43,
                        718
                    ],
                    [
                        93,
                        767
                    ]
                ],
                "interior": []
            }
        },
        {
            "id": 98178368,
            "classId": 6509560,
            "description": "",
            "geometryType": "rectangle",
            "labelerLogin": "inbox@datasetninja.com",
            "createdAt": "2023-12-15T16:14:08.547Z",
            "updatedAt": "2023-12-15T16:14:08.547Z",
            "tags": [],
            "classTitle": "trophozoite",
            "points": {
                "exterior": [
                    [
                        540,
                        741
                    ],
                    [
                        590,
                        767
                    ]
                ],
                "interior": []
            }
        },
        {
            "id": 98178367,
            "classId": 6509560,
            "description": "",
            "geometryType": "rectangle",
            "labelerLogin": "inbox@datasetninja.com",
            "createdAt": "2023-12-15T16:14:08.547Z",
            "updatedAt": "2023-12-15T16:14:08.547Z",
            "tags": [],
            "classTitle": "trophozoite",
            "points": {
                "exterior": [
                    [
                        627,
                        704
                    ],
                    [
                        677,
                        754
                    ]
                ],
                "interior": []
            }
        },
        {
            "id": 98178366,
            "classId": 6509560,
            "description": "",
            "geometryType": "rectangle",
            "labelerLogin": "inbox@datasetninja.com",
            "createdAt": "2023-12-15T16:14:08.546Z",
            "updatedAt": "2023-12-15T16:14:08.546Z",
            "tags": [],
            "classTitle": "trophozoite",
            "points": {
                "exterior": [
                    [
                        738,
                        408
                    ],
                    [
                        788,
                        458
                    ]
                ],
                "interior": []
            }
        },
        {
            "id": 98178365,
            "classId": 6509560,
            "description": "",
            "geometryType": "rectangle",
            "labelerLogin": "inbox@datasetninja.com",
            "createdAt": "2023-12-15T16:14:08.546Z",
            "updatedAt": "2023-12-15T16:14:08.546Z",
            "tags": [],
            "classTitle": "trophozoite",
            "points": {
                "exterior": [
                    [
                        785,
                        424
                    ],
                    [
                        835,
                        474
                    ]
                ],
                "interior": []
            }
        },
        {
            "id": 98178364,
            "classId": 6509560,
            "description": "",
            "geometryType": "rectangle",
            "labelerLogin": "inbox@datasetninja.com",
            "createdAt": "2023-12-15T16:14:08.546Z",
            "updatedAt": "2023-12-15T16:14:08.546Z",
            "tags": [],
            "classTitle": "trophozoite",
            "points": {
                "exterior": [
                    [
                        517,
                        221
                    ],
                    [
                        567,
                        271
                    ]
                ],
                "interior": []
            }
        },
        {
            "id": 98178363,
            "classId": 6509560,
            "description": "",
            "geometryType": "rectangle",
            "labelerLogin": "inbox@datasetninja.com",
            "createdAt": "2023-12-15T16:14:08.545Z",
            "updatedAt": "2023-12-15T16:14:08.545Z",
            "tags": [],
            "classTitle": "trophozoite",
            "points": {
                "exterior": [
                    [
                        973,
                        169
                    ],
                    [
                        1023,
                        219
                    ]
                ],
                "interior": []
            }
        },
        {
            "id": 98178362,
            "classId": 6509560,
            "description": "",
            "geometryType": "rectangle",
            "labelerLogin": "inbox@datasetninja.com",
            "createdAt": "2023-12-15T16:14:08.545Z",
            "updatedAt": "2023-12-15T16:14:08.545Z",
            "tags": [],
            "classTitle": "trophozoite",
            "points": {
                "exterior": [
                    [
                        990,
                        127
                    ],
                    [
                        1023,
                        177
                    ]
                ],
                "interior": []
            }
        },
        {
            "id": 98178361,
            "classId": 6509560,
            "description": "",
            "geometryType": "rectangle",
            "labelerLogin": "inbox@datasetninja.com",
            "createdAt": "2023-12-15T16:14:08.545Z",
            "updatedAt": "2023-12-15T16:14:08.545Z",
            "tags": [],
            "classTitle": "trophozoite",
            "points": {
                "exterior": [
                    [
                        286,
                        384
                    ],
                    [
                        336,
                        434
                    ]
                ],
                "interior": []
            }
        },
        {
            "id": 98178360,
            "classId": 6509560,
            "description": "",
            "geometryType": "rectangle",
            "labelerLogin": "inbox@datasetninja.com",
            "createdAt": "2023-12-15T16:14:08.545Z",
            "updatedAt": "2023-12-15T16:14:08.545Z",
            "tags": [],
            "classTitle": "trophozoite",
            "points": {
                "exterior": [
                    [
                        639,
                        556
                    ],
                    [
                        689,
                        606
                    ]
                ],
                "interior": []
            }
        }
    ]
}