{
    "description": "",
    "tags": [],
    "size": {
        "height": 768,
        "width": 1024
    },
    "objects": [
        {
            "id": 98152955,
            "classId": 6509560,
            "description": "",
            "geometryType": "rectangle",
            "labelerLogin": "inbox@datasetninja.com",
            "createdAt": "2023-12-15T16:13:19.005Z",
            "updatedAt": "2023-12-15T16:13:19.005Z",
            "tags": [],
            "classTitle": "trophozoite",
            "points": {
                "exterior": [
                    [
                        0,
                        333
                    ],
                    [
                        39,
                        383
                    ]
                ],
                "interior": []
            }
        },
        {
            "id": 98152954,
            "classId": 6509560,
            "description": "",
            "geometryType": "rectangle",
            "labelerLogin": "inbox@datasetninja.com",
            "createdAt": "2023-12-15T16:13:19.005Z",
            "updatedAt": "2023-12-15T16:13:19.005Z",
            "tags": [],
            "classTitle": "trophozoite",
            "points": {
                "exterior": [
                    [
                        0,
                        267
                    ],
                    [
                        43,
                        317
                    ]
                ],
                "interior": []
            }
        },
        {
            "id": 98152953,
            "classId": 6509560,
            "description": "",
            "geometryType": "rectangle",
            "labelerLogin": "inbox@datasetninja.com",
            "createdAt": "2023-12-15T16:13:19.005Z",
            "updatedAt": "2023-12-15T16:13:19.005Z",
            "tags": [],
            "classTitle": "trophozoite",
            "points": {
                "exterior": [
                    [
                        11,
                        199
                    ],
                    [
                        63,
                        249
                    ]
                ],
                "interior": []
            }
        },
        {
            "id": 98152952,
            "classId": 6509560,
            "description": "",
            "geometryType": "rectangle",
            "labelerLogin": "inbox@datasetninja.com",
            "createdAt": "2023-12-15T16:13:19.005Z",
            "updatedAt": "2023-12-15T16:13:19.005Z",
            "tags": [],
            "classTitle": "trophozoite",
            "points": {
                "exterior": [
                    [
                        69,
                        101
                    ],
                    [
                        120,
                        151
                    ]
                ],
                "interior": []
            }
        },
        {
            "id": 98152951,
            "classId": 6509560,
            "description": "",
            "geometryType": "rectangle",
            "labelerLogin": "inbox@datasetninja.com",
            "createdAt": "2023-12-15T16:13:19.004Z",
            "updatedAt": "2023-12-15T16:13:19.004Z",
            "tags": [],
            "classTitle": "trophozoite",
            "points": {
                "exterior": [
                    [
                        109,
                        68
                    ],
                    [
                        159,
                        118
                    ]
                ],
                "interior": []
            }
        },
        {
            "id": 98152950,
            "classId": 6509560,
            "description": "",
            "geometryType": "rectangle",
            "labelerLogin": "inbox@datasetninja.com",
            "createdAt": "2023-12-15T16:13:19.003Z",
            "updatedAt": "2023-12-15T16:13:19.003Z",
            "tags": [],
            "classTitle": "trophozoite",
            "points": {
                "exterior": [
                    [
                        417,
                        90
                    ],
                    [
                        467,
                        140
                    ]
                ],
                "interior": []
            }
        },
        {
            "id": 98152949,
            "classId": 6509560,
            "description": "",
            "geometryType": "rectangle",
            "labelerLogin": "inbox@datasetninja.com",
            "createdAt": "2023-12-15T16:13:19.003Z",
            "updatedAt": "2023-12-15T16:13:19.003Z",
            "tags": [],
            "classTitle": "trophozoite",
            "points": {
                "exterior": [
                    [
                        568,
                        459
                    ],
                    [
                        618,
                        509
                    ]
                ],
                "interior": []
            }
        },
        {
            "id": 98152948,
            "classId": 6509560,
            "description": "",
            "geometryType": "rectangle",
            "labelerLogin": "inbox@datasetninja.com",
            "createdAt": "2023-12-15T16:13:19.002Z",
            "updatedAt": "2023-12-15T16:13:19.002Z",
            "tags": [],
            "classTitle": "trophozoite",
            "points": {
                "exterior": [
                    [
                        538,
                        398
                    ],
                    [
                        588,
                        448
                    ]
                ],
                "interior": []
            }
        },
        {
            "id": 98152947,
            "classId": 6509560,
            "description": "",
            "geometryType": "rectangle",
            "labelerLogin": "inbox@datasetninja.com",
            "createdAt": "2023-12-15T16:13:19.002Z",
            "updatedAt": "2023-12-15T16:13:19.002Z",
            "tags": [],
            "classTitle": "trophozoite",
            "points": {
                "exterior": [
                    [
                        434,
                        263
                    ],
                    [
                        484,
                        313
                    ]
                ],
                "interior": []
            }
        },
        {
            "id": 98152946,
            "classId": 6509560,
            "description": "",
            "geometryType": "rectangle",
            "labelerLogin": "inbox@datasetninja.com",
            "createdAt": "2023-12-15T16:13:19.002Z",
            "updatedAt": "2023-12-15T16:13:19.002Z",
            "tags": [],
            "classTitle": "trophozoite",
            "points": {
                "exterior": [
                    [
                        433,
                        222
                    ],
                    [
                        483,
                        272
                    ]
                ],
                "interior": []
            }
        },
        {
            "id": 98152945,
            "classId": 6509560,
            "description": "",
            "geometryType": "rectangle",
            "labelerLogin": "inbox@datasetninja.com",
            "createdAt": "2023-12-15T16:13:19.001Z",
            "updatedAt": "2023-12-15T16:13:19.001Z",
            "tags": [],
            "classTitle": "trophozoite",
            "points": {
                "exterior": [
                    [
                        15,
                        714
                    ],
                    [
                        65,
                        764
                    ]
                ],
                "interior": []
            }
        },
        {
            "id": 98152944,
            "classId": 6509560,
            "description": "",
            "geometryType": "rectangle",
            "labelerLogin": "inbox@datasetninja.com",
            "createdAt": "2023-12-15T16:13:19.001Z",
            "updatedAt": "2023-12-15T16:13:19.001Z",
            "tags": [],
            "classTitle": "trophozoite",
            "points": {
                "exterior": [
                    [
                        57,
                        731
                    ],
                    [
                        107,
                        767
                    ]
                ],
                "interior": []
            }
        },
        {
            "id": 98152943,
            "classId": 6509560,
            "description": "",
            "geometryType": "rectangle",
            "labelerLogin": "inbox@datasetninja.com",
            "createdAt": "2023-12-15T16:13:19.001Z",
            "updatedAt": "2023-12-15T16:13:19.001Z",
            "tags": [],
            "classTitle": "trophozoite",
            "points": {
                "exterior": [
                    [
                        201,
                        703
                    ],
                    [
                        251,
                        753
                    ]
                ],
                "interior": []
            }
        },
        {
            "id": 98152942,
            "classId": 6509560,
            "description": "",
            "geometryType": "rectangle",
            "labelerLogin": "inbox@datasetninja.com",
            "createdAt": "2023-12-15T16:13:19.000Z",
            "updatedAt": "2023-12-15T16:13:19.000Z",
            "tags": [],
            "classTitle": "trophozoite",
            "points": {
                "exterior": [
                    [
                        298,
                        681
                    ],
                    [
                        348,
                        731
                    ]
                ],
                "interior": []
            }
        },
        {
            "id": 98152941,
            "classId": 6509560,
            "description": "",
            "geometryType": "rectangle",
            "labelerLogin": "inbox@datasetninja.com",
            "createdAt": "2023-12-15T16:13:19.000Z",
            "updatedAt": "2023-12-15T16:13:19.000Z",
            "tags": [],
            "classTitle": "trophozoite",
            "points": {
                "exterior": [
                    [
                        264,
                        582
                    ],
                    [
                        315,
                        632
                    ]
                ],
                "interior": []
            }
        },
        {
            "id": 98152940,
            "classId": 6509560,
            "description": "",
            "geometryType": "rectangle",
            "labelerLogin": "inbox@datasetninja.com",
            "createdAt": "2023-12-15T16:13:18.999Z",
            "updatedAt": "2023-12-15T16:13:18.999Z",
            "tags": [],
            "classTitle": "trophozoite",
            "points": {
                "exterior": [
                    [
                        148,
                        306
                    ],
                    [
                        198,
                        356
                    ]
                ],
                "interior": []
            }
        },
        {
            "id": 98152939,
            "classId": 6509560,
            "description": "",
            "geometryType": "rectangle",
            "labelerLogin": "inbox@datasetninja.com",
            "createdAt": "2023-12-15T16:13:18.999Z",
            "updatedAt": "2023-12-15T16:13:18.999Z",
            "tags": [],
            "classTitle": "trophozoite",
            "points": {
                "exterior": [
                    [
                        534,
                        546
                    ],
                    [
                        584,
                        596
                    ]
                ],
                "interior": []
            }
        },
        {
            "id": 98152938,
            "classId": 6509560,
            "description": "",
            "geometryType": "rectangle",
            "labelerLogin": "inbox@datasetninja.com",
            "createdAt": "2023-12-15T16:13:18.999Z",
            "updatedAt": "2023-12-15T16:13:18.999Z",
            "tags": [],
            "classTitle": "trophozoite",
            "points": {
                "exterior": [
                    [
                        454,
                        657
                    ],
                    [
                        504,
                        707
                    ]
                ],
                "interior": []
            }
        },
        {
            "id": 98152937,
            "classId": 6509560,
            "description": "",
            "geometryType": "rectangle",
            "labelerLogin": "inbox@datasetninja.com",
            "createdAt": "2023-12-15T16:13:18.999Z",
            "updatedAt": "2023-12-15T16:13:18.999Z",
            "tags": [],
            "classTitle": "trophozoite",
            "points": {
                "exterior": [
                    [
                        753,
                        551
                    ],
                    [
                        803,
                        601
                    ]
                ],
                "interior": []
            }
        },
        {
            "id": 98152936,
            "classId": 6509560,
            "description": "",
            "geometryType": "rectangle",
            "labelerLogin": "inbox@datasetninja.com",
            "createdAt": "2023-12-15T16:13:18.998Z",
            "updatedAt": "2023-12-15T16:13:18.998Z",
            "tags": [],
            "classTitle": "trophozoite",
            "points": {
                "exterior": [
                    [
                        783,
                        714
                    ],
                    [
                        833,
                        764
                    ]
                ],
                "interior": []
            }
        },
        {
            "id": 98152935,
            "classId": 6509560,
            "description": "",
            "geometryType": "rectangle",
            "labelerLogin": "inbox@datasetninja.com",
            "createdAt": "2023-12-15T16:13:18.998Z",
            "updatedAt": "2023-12-15T16:13:18.998Z",
            "tags": [],
            "classTitle": "trophozoite",
            "points": {
                "exterior": [
                    [
                        542,
                        731
                    ],
                    [
                        592,
                        767
                    ]
                ],
                "interior": []
            }
        },
        {
            "id": 98152934,
            "classId": 6509560,
            "description": "",
            "geometryType": "rectangle",
            "labelerLogin": "inbox@datasetninja.com",
            "createdAt": "2023-12-15T16:13:18.998Z",
            "updatedAt": "2023-12-15T16:13:18.998Z",
            "tags": [],
            "classTitle": "trophozoite",
            "points": {
                "exterior": [
                    [
                        970,
                        666
                    ],
                    [
                        1020,
                        716
                    ]
                ],
                "interior": []
            }
        },
        {
            "id": 98152933,
            "classId": 6509560,
            "description": "",
            "geometryType": "rectangle",
            "labelerLogin": "inbox@datasetninja.com",
            "createdAt": "2023-12-15T16:13:18.998Z",
            "updatedAt": "2023-12-15T16:13:18.998Z",
            "tags": [],
            "classTitle": "trophozoite",
            "points": {
                "exterior": [
                    [
                        843,
                        83
                    ],
                    [
                        893,
                        133
                    ]
                ],
                "interior": []
            }
        },
        {
            "id": 98152932,
            "classId": 6509560,
            "description": "",
            "geometryType": "rectangle",
            "labelerLogin": "inbox@datasetninja.com",
            "createdAt": "2023-12-15T16:13:18.998Z",
            "updatedAt": "2023-12-15T16:13:18.998Z",
            "tags": [],
            "classTitle": "trophozoite",
            "points": {
                "exterior": [
                    [
                        971,
                        117
                    ],
                    [
                        1021,
                        167
                    ]
                ],
                "interior": []
            }
        },
        {
            "id": 98152931,
            "classId": 6509560,
            "description": "",
            "geometryType": "rectangle",
            "labelerLogin": "inbox@datasetninja.com",
            "createdAt": "2023-12-15T16:13:18.997Z",
            "updatedAt": "2023-12-15T16:13:18.997Z",
            "tags": [],
            "classTitle": "trophozoite",
            "points": {
                "exterior": [
                    [
                        979,
                        66
                    ],
                    [
                        1023,
                        116
                    ]
                ],
                "interior": []
            }
        },
        {
            "id": 98152930,
            "classId": 6509560,
            "description": "",
            "geometryType": "rectangle",
            "labelerLogin": "inbox@datasetninja.com",
            "createdAt": "2023-12-15T16:13:18.997Z",
            "updatedAt": "2023-12-15T16:13:18.997Z",
            "tags": [],
            "classTitle": "trophozoite",
            "points": {
                "exterior": [
                    [
                        862,
                        297
                    ],
                    [
                        912,
                        347
                    ]
                ],
                "interior": []
            }
        },
        {
            "id": 98152929,
            "classId": 6509560,
            "description": "",
            "geometryType": "rectangle",
            "labelerLogin": "inbox@datasetninja.com",
            "createdAt": "2023-12-15T16:13:18.997Z",
            "updatedAt": "2023-12-15T16:13:18.997Z",
            "tags": [],
            "classTitle": "trophozoite",
            "points": {
                "exterior": [
                    [
                        770,
                        432
                    ],
                    [
                        820,
                        482
                    ]
                ],
                "interior": []
            }
        },
        {
            "id": 98152928,
            "classId": 6509560,
            "description": "",
            "geometryType": "rectangle",
            "labelerLogin": "inbox@datasetninja.com",
            "createdAt": "2023-12-15T16:13:18.996Z",
            "updatedAt": "2023-12-15T16:13:18.996Z",
            "tags": [],
            "classTitle": "trophozoite",
            "points": {
                "exterior": [
                    [
                        231,
                        412
                    ],
                    [
                        281,
                        462
                    ]
                ],
                "interior": []
            }
        },
        {
            "id": 98152927,
            "classId": 6509560,
            "description": "",
            "geometryType": "rectangle",
            "labelerLogin": "inbox@datasetninja.com",
            "createdAt": "2023-12-15T16:13:18.996Z",
            "updatedAt": "2023-12-15T16:13:18.996Z",
            "tags": [],
            "classTitle": "trophozoite",
            "points": {
                "exterior": [
                    [
                        430,
                        557
                    ],
                    [
                        480,
                        607
                    ]
                ],
                "interior": []
            }
        },
        {
            "id": 98152926,
            "classId": 6509560,
            "description": "",
            "geometryType": "rectangle",
            "labelerLogin": "inbox@datasetninja.com",
            "createdAt": "2023-12-15T16:13:18.996Z",
            "updatedAt": "2023-12-15T16:13:18.996Z",
            "tags": [],
            "classTitle": "trophozoite",
            "points": {
                "exterior": [
                    [
                        254,
                        68
                    ],
                    [
                        304,
                        118
                    ]
                ],
                "interior": []
            }
        }
    ]
}