{
    "description": "",
    "tags": [],
    "size": {
        "height": 768,
        "width": 1024
    },
    "objects": [
        {
            "id": 98147446,
            "classId": 6509560,
            "description": "",
            "geometryType": "rectangle",
            "labelerLogin": "inbox@datasetninja.com",
            "createdAt": "2023-12-15T16:13:07.730Z",
            "updatedAt": "2023-12-15T16:13:07.730Z",
            "tags": [],
            "classTitle": "trophozoite",
            "points": {
                "exterior": [
                    [
                        808,
                        90
                    ],
                    [
                        892,
                        176
                    ]
                ],
                "interior": []
            }
        }
    ]
}