{
    "description": "",
    "tags": [],
    "size": {
        "height": 768,
        "width": 1024
    },
    "objects": [
        {
            "id": 98152550,
            "classId": 6509560,
            "description": "",
            "geometryType": "rectangle",
            "labelerLogin": "inbox@datasetninja.com",
            "createdAt": "2023-12-15T16:13:17.938Z",
            "updatedAt": "2023-12-15T16:13:17.938Z",
            "tags": [],
            "classTitle": "trophozoite",
            "points": {
                "exterior": [
                    [
                        191,
                        584
                    ],
                    [
                        241,
                        634
                    ]
                ],
                "interior": []
            }
        },
        {
            "id": 98152549,
            "classId": 6509560,
            "description": "",
            "geometryType": "rectangle",
            "labelerLogin": "inbox@datasetninja.com",
            "createdAt": "2023-12-15T16:13:17.938Z",
            "updatedAt": "2023-12-15T16:13:17.938Z",
            "tags": [],
            "classTitle": "trophozoite",
            "points": {
                "exterior": [
                    [
                        231,
                        388
                    ],
                    [
                        281,
                        438
                    ]
                ],
                "interior": []
            }
        },
        {
            "id": 98152548,
            "classId": 6509560,
            "description": "",
            "geometryType": "rectangle",
            "labelerLogin": "inbox@datasetninja.com",
            "createdAt": "2023-12-15T16:13:17.937Z",
            "updatedAt": "2023-12-15T16:13:17.937Z",
            "tags": [],
            "classTitle": "trophozoite",
            "points": {
                "exterior": [
                    [
                        513,
                        282
                    ],
                    [
                        563,
                        332
                    ]
                ],
                "interior": []
            }
        },
        {
            "id": 98152547,
            "classId": 6509560,
            "description": "",
            "geometryType": "rectangle",
            "labelerLogin": "inbox@datasetninja.com",
            "createdAt": "2023-12-15T16:13:17.937Z",
            "updatedAt": "2023-12-15T16:13:17.937Z",
            "tags": [],
            "classTitle": "trophozoite",
            "points": {
                "exterior": [
                    [
                        755,
                        76
                    ],
                    [
                        806,
                        126
                    ]
                ],
                "interior": []
            }
        },
        {
            "id": 98152546,
            "classId": 6509560,
            "description": "",
            "geometryType": "rectangle",
            "labelerLogin": "inbox@datasetninja.com",
            "createdAt": "2023-12-15T16:13:17.937Z",
            "updatedAt": "2023-12-15T16:13:17.937Z",
            "tags": [],
            "classTitle": "trophozoite",
            "points": {
                "exterior": [
                    [
                        728,
                        298
                    ],
                    [
                        780,
                        348
                    ]
                ],
                "interior": []
            }
        },
        {
            "id": 98152545,
            "classId": 6509560,
            "description": "",
            "geometryType": "rectangle",
            "labelerLogin": "inbox@datasetninja.com",
            "createdAt": "2023-12-15T16:13:17.937Z",
            "updatedAt": "2023-12-15T16:13:17.937Z",
            "tags": [],
            "classTitle": "trophozoite",
            "points": {
                "exterior": [
                    [
                        643,
                        417
                    ],
                    [
                        693,
                        467
                    ]
                ],
                "interior": []
            }
        },
        {
            "id": 98152544,
            "classId": 6509560,
            "description": "",
            "geometryType": "rectangle",
            "labelerLogin": "inbox@datasetninja.com",
            "createdAt": "2023-12-15T16:13:17.937Z",
            "updatedAt": "2023-12-15T16:13:17.937Z",
            "tags": [],
            "classTitle": "trophozoite",
            "points": {
                "exterior": [
                    [
                        924,
                        227
                    ],
                    [
                        974,
                        277
                    ]
                ],
                "interior": []
            }
        },
        {
            "id": 98152543,
            "classId": 6509560,
            "description": "",
            "geometryType": "rectangle",
            "labelerLogin": "inbox@datasetninja.com",
            "createdAt": "2023-12-15T16:13:17.936Z",
            "updatedAt": "2023-12-15T16:13:17.936Z",
            "tags": [],
            "classTitle": "trophozoite",
            "points": {
                "exterior": [
                    [
                        905,
                        323
                    ],
                    [
                        955,
                        373
                    ]
                ],
                "interior": []
            }
        },
        {
            "id": 98152542,
            "classId": 6509560,
            "description": "",
            "geometryType": "rectangle",
            "labelerLogin": "inbox@datasetninja.com",
            "createdAt": "2023-12-15T16:13:17.936Z",
            "updatedAt": "2023-12-15T16:13:17.936Z",
            "tags": [],
            "classTitle": "trophozoite",
            "points": {
                "exterior": [
                    [
                        127,
                        14
                    ],
                    [
                        177,
                        64
                    ]
                ],
                "interior": []
            }
        },
        {
            "id": 98152541,
            "classId": 6509560,
            "description": "",
            "geometryType": "rectangle",
            "labelerLogin": "inbox@datasetninja.com",
            "createdAt": "2023-12-15T16:13:17.936Z",
            "updatedAt": "2023-12-15T16:13:17.936Z",
            "tags": [],
            "classTitle": "trophozoite",
            "points": {
                "exterior": [
                    [
                        181,
                        146
                    ],
                    [
                        232,
                        196
                    ]
                ],
                "interior": []
            }
        },
        {
            "id": 98152540,
            "classId": 6509560,
            "description": "",
            "geometryType": "rectangle",
            "labelerLogin": "inbox@datasetninja.com",
            "createdAt": "2023-12-15T16:13:17.936Z",
            "updatedAt": "2023-12-15T16:13:17.936Z",
            "tags": [],
            "classTitle": "trophozoite",
            "points": {
                "exterior": [
                    [
                        13,
                        231
                    ],
                    [
                        63,
                        281
                    ]
                ],
                "interior": []
            }
        },
        {
            "id": 98152539,
            "classId": 6509560,
            "description": "",
            "geometryType": "rectangle",
            "labelerLogin": "inbox@datasetninja.com",
            "createdAt": "2023-12-15T16:13:17.935Z",
            "updatedAt": "2023-12-15T16:13:17.935Z",
            "tags": [],
            "classTitle": "trophozoite",
            "points": {
                "exterior": [
                    [
                        364,
                        643
                    ],
                    [
                        414,
                        693
                    ]
                ],
                "interior": []
            }
        }
    ]
}