{
    "description": "",
    "tags": [],
    "size": {
        "height": 768,
        "width": 1024
    },
    "objects": [
        {
            "id": 98175982,
            "classId": 6509560,
            "description": "",
            "geometryType": "rectangle",
            "labelerLogin": "inbox@datasetninja.com",
            "createdAt": "2023-12-15T16:14:03.883Z",
            "updatedAt": "2023-12-15T16:14:03.883Z",
            "tags": [],
            "classTitle": "trophozoite",
            "points": {
                "exterior": [
                    [
                        697,
                        46
                    ],
                    [
                        749,
                        96
                    ]
                ],
                "interior": []
            }
        },
        {
            "id": 98175981,
            "classId": 6509560,
            "description": "",
            "geometryType": "rectangle",
            "labelerLogin": "inbox@datasetninja.com",
            "createdAt": "2023-12-15T16:14:03.883Z",
            "updatedAt": "2023-12-15T16:14:03.883Z",
            "tags": [],
            "classTitle": "trophozoite",
            "points": {
                "exterior": [
                    [
                        802,
                        144
                    ],
                    [
                        852,
                        194
                    ]
                ],
                "interior": []
            }
        },
        {
            "id": 98175980,
            "classId": 6509560,
            "description": "",
            "geometryType": "rectangle",
            "labelerLogin": "inbox@datasetninja.com",
            "createdAt": "2023-12-15T16:14:03.882Z",
            "updatedAt": "2023-12-15T16:14:03.882Z",
            "tags": [],
            "classTitle": "trophozoite",
            "points": {
                "exterior": [
                    [
                        922,
                        0
                    ],
                    [
                        972,
                        48
                    ]
                ],
                "interior": []
            }
        },
        {
            "id": 98175979,
            "classId": 6509560,
            "description": "",
            "geometryType": "rectangle",
            "labelerLogin": "inbox@datasetninja.com",
            "createdAt": "2023-12-15T16:14:03.882Z",
            "updatedAt": "2023-12-15T16:14:03.882Z",
            "tags": [],
            "classTitle": "trophozoite",
            "points": {
                "exterior": [
                    [
                        782,
                        52
                    ],
                    [
                        832,
                        102
                    ]
                ],
                "interior": []
            }
        },
        {
            "id": 98175978,
            "classId": 6509560,
            "description": "",
            "geometryType": "rectangle",
            "labelerLogin": "inbox@datasetninja.com",
            "createdAt": "2023-12-15T16:14:03.882Z",
            "updatedAt": "2023-12-15T16:14:03.882Z",
            "tags": [],
            "classTitle": "trophozoite",
            "points": {
                "exterior": [
                    [
                        620,
                        39
                    ],
                    [
                        670,
                        89
                    ]
                ],
                "interior": []
            }
        },
        {
            "id": 98175977,
            "classId": 6509560,
            "description": "",
            "geometryType": "rectangle",
            "labelerLogin": "inbox@datasetninja.com",
            "createdAt": "2023-12-15T16:14:03.882Z",
            "updatedAt": "2023-12-15T16:14:03.882Z",
            "tags": [],
            "classTitle": "trophozoite",
            "points": {
                "exterior": [
                    [
                        489,
                        264
                    ],
                    [
                        540,
                        314
                    ]
                ],
                "interior": []
            }
        },
        {
            "id": 98175976,
            "classId": 6509560,
            "description": "",
            "geometryType": "rectangle",
            "labelerLogin": "inbox@datasetninja.com",
            "createdAt": "2023-12-15T16:14:03.882Z",
            "updatedAt": "2023-12-15T16:14:03.882Z",
            "tags": [],
            "classTitle": "trophozoite",
            "points": {
                "exterior": [
                    [
                        362,
                        300
                    ],
                    [
                        412,
                        350
                    ]
                ],
                "interior": []
            }
        },
        {
            "id": 98175975,
            "classId": 6509560,
            "description": "",
            "geometryType": "rectangle",
            "labelerLogin": "inbox@datasetninja.com",
            "createdAt": "2023-12-15T16:14:03.881Z",
            "updatedAt": "2023-12-15T16:14:03.881Z",
            "tags": [],
            "classTitle": "trophozoite",
            "points": {
                "exterior": [
                    [
                        317,
                        306
                    ],
                    [
                        367,
                        356
                    ]
                ],
                "interior": []
            }
        },
        {
            "id": 98175974,
            "classId": 6509560,
            "description": "",
            "geometryType": "rectangle",
            "labelerLogin": "inbox@datasetninja.com",
            "createdAt": "2023-12-15T16:14:03.881Z",
            "updatedAt": "2023-12-15T16:14:03.881Z",
            "tags": [],
            "classTitle": "trophozoite",
            "points": {
                "exterior": [
                    [
                        114,
                        323
                    ],
                    [
                        164,
                        373
                    ]
                ],
                "interior": []
            }
        },
        {
            "id": 98175973,
            "classId": 6509560,
            "description": "",
            "geometryType": "rectangle",
            "labelerLogin": "inbox@datasetninja.com",
            "createdAt": "2023-12-15T16:14:03.881Z",
            "updatedAt": "2023-12-15T16:14:03.881Z",
            "tags": [],
            "classTitle": "trophozoite",
            "points": {
                "exterior": [
                    [
                        247,
                        110
                    ],
                    [
                        297,
                        160
                    ]
                ],
                "interior": []
            }
        },
        {
            "id": 98175972,
            "classId": 6509560,
            "description": "",
            "geometryType": "rectangle",
            "labelerLogin": "inbox@datasetninja.com",
            "createdAt": "2023-12-15T16:14:03.881Z",
            "updatedAt": "2023-12-15T16:14:03.881Z",
            "tags": [],
            "classTitle": "trophozoite",
            "points": {
                "exterior": [
                    [
                        528,
                        684
                    ],
                    [
                        578,
                        734
                    ]
                ],
                "interior": []
            }
        },
        {
            "id": 98175971,
            "classId": 6509560,
            "description": "",
            "geometryType": "rectangle",
            "labelerLogin": "inbox@datasetninja.com",
            "createdAt": "2023-12-15T16:14:03.881Z",
            "updatedAt": "2023-12-15T16:14:03.881Z",
            "tags": [],
            "classTitle": "trophozoite",
            "points": {
                "exterior": [
                    [
                        737,
                        725
                    ],
                    [
                        787,
                        767
                    ]
                ],
                "interior": []
            }
        }
    ]
}