{
    "description": "",
    "tags": [],
    "size": {
        "height": 768,
        "width": 1024
    },
    "objects": [
        {
            "id": 98179977,
            "classId": 6509560,
            "description": "",
            "geometryType": "rectangle",
            "labelerLogin": "inbox@datasetninja.com",
            "createdAt": "2023-12-15T16:14:11.843Z",
            "updatedAt": "2023-12-15T16:14:11.843Z",
            "tags": [],
            "classTitle": "trophozoite",
            "points": {
                "exterior": [
                    [
                        126,
                        673
                    ],
                    [
                        176,
                        723
                    ]
                ],
                "interior": []
            }
        },
        {
            "id": 98179976,
            "classId": 6509560,
            "description": "",
            "geometryType": "rectangle",
            "labelerLogin": "inbox@datasetninja.com",
            "createdAt": "2023-12-15T16:14:11.842Z",
            "updatedAt": "2023-12-15T16:14:11.842Z",
            "tags": [],
            "classTitle": "trophozoite",
            "points": {
                "exterior": [
                    [
                        321,
                        496
                    ],
                    [
                        372,
                        546
                    ]
                ],
                "interior": []
            }
        },
        {
            "id": 98179975,
            "classId": 6509560,
            "description": "",
            "geometryType": "rectangle",
            "labelerLogin": "inbox@datasetninja.com",
            "createdAt": "2023-12-15T16:14:11.842Z",
            "updatedAt": "2023-12-15T16:14:11.842Z",
            "tags": [],
            "classTitle": "trophozoite",
            "points": {
                "exterior": [
                    [
                        429,
                        166
                    ],
                    [
                        479,
                        216
                    ]
                ],
                "interior": []
            }
        },
        {
            "id": 98179974,
            "classId": 6509560,
            "description": "",
            "geometryType": "rectangle",
            "labelerLogin": "inbox@datasetninja.com",
            "createdAt": "2023-12-15T16:14:11.842Z",
            "updatedAt": "2023-12-15T16:14:11.842Z",
            "tags": [],
            "classTitle": "trophozoite",
            "points": {
                "exterior": [
                    [
                        487,
                        89
                    ],
                    [
                        537,
                        140
                    ]
                ],
                "interior": []
            }
        },
        {
            "id": 98179973,
            "classId": 6509560,
            "description": "",
            "geometryType": "rectangle",
            "labelerLogin": "inbox@datasetninja.com",
            "createdAt": "2023-12-15T16:14:11.841Z",
            "updatedAt": "2023-12-15T16:14:11.841Z",
            "tags": [],
            "classTitle": "trophozoite",
            "points": {
                "exterior": [
                    [
                        859,
                        263
                    ],
                    [
                        909,
                        313
                    ]
                ],
                "interior": []
            }
        },
        {
            "id": 98179972,
            "classId": 6509560,
            "description": "",
            "geometryType": "rectangle",
            "labelerLogin": "inbox@datasetninja.com",
            "createdAt": "2023-12-15T16:14:11.841Z",
            "updatedAt": "2023-12-15T16:14:11.841Z",
            "tags": [],
            "classTitle": "trophozoite",
            "points": {
                "exterior": [
                    [
                        765,
                        259
                    ],
                    [
                        815,
                        309
                    ]
                ],
                "interior": []
            }
        },
        {
            "id": 98179971,
            "classId": 6509560,
            "description": "",
            "geometryType": "rectangle",
            "labelerLogin": "inbox@datasetninja.com",
            "createdAt": "2023-12-15T16:14:11.840Z",
            "updatedAt": "2023-12-15T16:14:11.840Z",
            "tags": [],
            "classTitle": "trophozoite",
            "points": {
                "exterior": [
                    [
                        466,
                        564
                    ],
                    [
                        516,
                        614
                    ]
                ],
                "interior": []
            }
        },
        {
            "id": 98179970,
            "classId": 6509560,
            "description": "",
            "geometryType": "rectangle",
            "labelerLogin": "inbox@datasetninja.com",
            "createdAt": "2023-12-15T16:14:11.840Z",
            "updatedAt": "2023-12-15T16:14:11.840Z",
            "tags": [],
            "classTitle": "trophozoite",
            "points": {
                "exterior": [
                    [
                        948,
                        503
                    ],
                    [
                        998,
                        554
                    ]
                ],
                "interior": []
            }
        },
        {
            "id": 98179969,
            "classId": 6509560,
            "description": "",
            "geometryType": "rectangle",
            "labelerLogin": "inbox@datasetninja.com",
            "createdAt": "2023-12-15T16:14:11.840Z",
            "updatedAt": "2023-12-15T16:14:11.840Z",
            "tags": [],
            "classTitle": "trophozoite",
            "points": {
                "exterior": [
                    [
                        992,
                        390
                    ],
                    [
                        1023,
                        440
                    ]
                ],
                "interior": []
            }
        },
        {
            "id": 98179968,
            "classId": 6509560,
            "description": "",
            "geometryType": "rectangle",
            "labelerLogin": "inbox@datasetninja.com",
            "createdAt": "2023-12-15T16:14:11.840Z",
            "updatedAt": "2023-12-15T16:14:11.840Z",
            "tags": [],
            "classTitle": "trophozoite",
            "points": {
                "exterior": [
                    [
                        855,
                        3
                    ],
                    [
                        905,
                        53
                    ]
                ],
                "interior": []
            }
        }
    ]
}