{
    "description": "",
    "tags": [],
    "size": {
        "height": 768,
        "width": 1024
    },
    "objects": [
        {
            "id": 98150153,
            "classId": 6509560,
            "description": "",
            "geometryType": "rectangle",
            "labelerLogin": "inbox@datasetninja.com",
            "createdAt": "2023-12-15T16:13:13.857Z",
            "updatedAt": "2023-12-15T16:13:13.857Z",
            "tags": [],
            "classTitle": "trophozoite",
            "points": {
                "exterior": [
                    [
                        48,
                        100
                    ],
                    [
                        98,
                        150
                    ]
                ],
                "interior": []
            }
        },
        {
            "id": 98150152,
            "classId": 6509560,
            "description": "",
            "geometryType": "rectangle",
            "labelerLogin": "inbox@datasetninja.com",
            "createdAt": "2023-12-15T16:13:13.857Z",
            "updatedAt": "2023-12-15T16:13:13.857Z",
            "tags": [],
            "classTitle": "trophozoite",
            "points": {
                "exterior": [
                    [
                        225,
                        20
                    ],
                    [
                        275,
                        70
                    ]
                ],
                "interior": []
            }
        },
        {
            "id": 98150151,
            "classId": 6509560,
            "description": "",
            "geometryType": "rectangle",
            "labelerLogin": "inbox@datasetninja.com",
            "createdAt": "2023-12-15T16:13:13.857Z",
            "updatedAt": "2023-12-15T16:13:13.857Z",
            "tags": [],
            "classTitle": "trophozoite",
            "points": {
                "exterior": [
                    [
                        250,
                        0
                    ],
                    [
                        300,
                        41
                    ]
                ],
                "interior": []
            }
        },
        {
            "id": 98150150,
            "classId": 6509560,
            "description": "",
            "geometryType": "rectangle",
            "labelerLogin": "inbox@datasetninja.com",
            "createdAt": "2023-12-15T16:13:13.857Z",
            "updatedAt": "2023-12-15T16:13:13.857Z",
            "tags": [],
            "classTitle": "trophozoite",
            "points": {
                "exterior": [
                    [
                        206,
                        207
                    ],
                    [
                        256,
                        257
                    ]
                ],
                "interior": []
            }
        },
        {
            "id": 98150149,
            "classId": 6509560,
            "description": "",
            "geometryType": "rectangle",
            "labelerLogin": "inbox@datasetninja.com",
            "createdAt": "2023-12-15T16:13:13.856Z",
            "updatedAt": "2023-12-15T16:13:13.856Z",
            "tags": [],
            "classTitle": "trophozoite",
            "points": {
                "exterior": [
                    [
                        257,
                        312
                    ],
                    [
                        307,
                        362
                    ]
                ],
                "interior": []
            }
        },
        {
            "id": 98150148,
            "classId": 6509560,
            "description": "",
            "geometryType": "rectangle",
            "labelerLogin": "inbox@datasetninja.com",
            "createdAt": "2023-12-15T16:13:13.856Z",
            "updatedAt": "2023-12-15T16:13:13.856Z",
            "tags": [],
            "classTitle": "trophozoite",
            "points": {
                "exterior": [
                    [
                        273,
                        254
                    ],
                    [
                        323,
                        304
                    ]
                ],
                "interior": []
            }
        },
        {
            "id": 98150147,
            "classId": 6509560,
            "description": "",
            "geometryType": "rectangle",
            "labelerLogin": "inbox@datasetninja.com",
            "createdAt": "2023-12-15T16:13:13.856Z",
            "updatedAt": "2023-12-15T16:13:13.856Z",
            "tags": [],
            "classTitle": "trophozoite",
            "points": {
                "exterior": [
                    [
                        305,
                        284
                    ],
                    [
                        355,
                        334
                    ]
                ],
                "interior": []
            }
        },
        {
            "id": 98150146,
            "classId": 6509560,
            "description": "",
            "geometryType": "rectangle",
            "labelerLogin": "inbox@datasetninja.com",
            "createdAt": "2023-12-15T16:13:13.856Z",
            "updatedAt": "2023-12-15T16:13:13.856Z",
            "tags": [],
            "classTitle": "trophozoite",
            "points": {
                "exterior": [
                    [
                        390,
                        278
                    ],
                    [
                        440,
                        328
                    ]
                ],
                "interior": []
            }
        },
        {
            "id": 98150145,
            "classId": 6509560,
            "description": "",
            "geometryType": "rectangle",
            "labelerLogin": "inbox@datasetninja.com",
            "createdAt": "2023-12-15T16:13:13.855Z",
            "updatedAt": "2023-12-15T16:13:13.855Z",
            "tags": [],
            "classTitle": "trophozoite",
            "points": {
                "exterior": [
                    [
                        488,
                        276
                    ],
                    [
                        538,
                        326
                    ]
                ],
                "interior": []
            }
        },
        {
            "id": 98150144,
            "classId": 6509560,
            "description": "",
            "geometryType": "rectangle",
            "labelerLogin": "inbox@datasetninja.com",
            "createdAt": "2023-12-15T16:13:13.855Z",
            "updatedAt": "2023-12-15T16:13:13.855Z",
            "tags": [],
            "classTitle": "trophozoite",
            "points": {
                "exterior": [
                    [
                        539,
                        251
                    ],
                    [
                        589,
                        301
                    ]
                ],
                "interior": []
            }
        },
        {
            "id": 98150143,
            "classId": 6509560,
            "description": "",
            "geometryType": "rectangle",
            "labelerLogin": "inbox@datasetninja.com",
            "createdAt": "2023-12-15T16:13:13.855Z",
            "updatedAt": "2023-12-15T16:13:13.855Z",
            "tags": [],
            "classTitle": "trophozoite",
            "points": {
                "exterior": [
                    [
                        545,
                        541
                    ],
                    [
                        595,
                        591
                    ]
                ],
                "interior": []
            }
        },
        {
            "id": 98150142,
            "classId": 6509560,
            "description": "",
            "geometryType": "rectangle",
            "labelerLogin": "inbox@datasetninja.com",
            "createdAt": "2023-12-15T16:13:13.855Z",
            "updatedAt": "2023-12-15T16:13:13.855Z",
            "tags": [],
            "classTitle": "trophozoite",
            "points": {
                "exterior": [
                    [
                        576,
                        575
                    ],
                    [
                        626,
                        625
                    ]
                ],
                "interior": []
            }
        },
        {
            "id": 98150141,
            "classId": 6509560,
            "description": "",
            "geometryType": "rectangle",
            "labelerLogin": "inbox@datasetninja.com",
            "createdAt": "2023-12-15T16:13:13.855Z",
            "updatedAt": "2023-12-15T16:13:13.855Z",
            "tags": [],
            "classTitle": "trophozoite",
            "points": {
                "exterior": [
                    [
                        588,
                        629
                    ],
                    [
                        638,
                        679
                    ]
                ],
                "interior": []
            }
        },
        {
            "id": 98150140,
            "classId": 6509560,
            "description": "",
            "geometryType": "rectangle",
            "labelerLogin": "inbox@datasetninja.com",
            "createdAt": "2023-12-15T16:13:13.855Z",
            "updatedAt": "2023-12-15T16:13:13.855Z",
            "tags": [],
            "classTitle": "trophozoite",
            "points": {
                "exterior": [
                    [
                        687,
                        699
                    ],
                    [
                        737,
                        749
                    ]
                ],
                "interior": []
            }
        },
        {
            "id": 98150139,
            "classId": 6509560,
            "description": "",
            "geometryType": "rectangle",
            "labelerLogin": "inbox@datasetninja.com",
            "createdAt": "2023-12-15T16:13:13.855Z",
            "updatedAt": "2023-12-15T16:13:13.855Z",
            "tags": [],
            "classTitle": "trophozoite",
            "points": {
                "exterior": [
                    [
                        816,
                        687
                    ],
                    [
                        866,
                        737
                    ]
                ],
                "interior": []
            }
        },
        {
            "id": 98150138,
            "classId": 6509560,
            "description": "",
            "geometryType": "rectangle",
            "labelerLogin": "inbox@datasetninja.com",
            "createdAt": "2023-12-15T16:13:13.854Z",
            "updatedAt": "2023-12-15T16:13:13.854Z",
            "tags": [],
            "classTitle": "trophozoite",
            "points": {
                "exterior": [
                    [
                        942,
                        604
                    ],
                    [
                        992,
                        654
                    ]
                ],
                "interior": []
            }
        },
        {
            "id": 98150137,
            "classId": 6509560,
            "description": "",
            "geometryType": "rectangle",
            "labelerLogin": "inbox@datasetninja.com",
            "createdAt": "2023-12-15T16:13:13.854Z",
            "updatedAt": "2023-12-15T16:13:13.854Z",
            "tags": [],
            "classTitle": "trophozoite",
            "points": {
                "exterior": [
                    [
                        679,
                        530
                    ],
                    [
                        729,
                        580
                    ]
                ],
                "interior": []
            }
        },
        {
            "id": 98150136,
            "classId": 6509560,
            "description": "",
            "geometryType": "rectangle",
            "labelerLogin": "inbox@datasetninja.com",
            "createdAt": "2023-12-15T16:13:13.854Z",
            "updatedAt": "2023-12-15T16:13:13.854Z",
            "tags": [],
            "classTitle": "trophozoite",
            "points": {
                "exterior": [
                    [
                        678,
                        427
                    ],
                    [
                        728,
                        477
                    ]
                ],
                "interior": []
            }
        },
        {
            "id": 98150135,
            "classId": 6509560,
            "description": "",
            "geometryType": "rectangle",
            "labelerLogin": "inbox@datasetninja.com",
            "createdAt": "2023-12-15T16:13:13.854Z",
            "updatedAt": "2023-12-15T16:13:13.854Z",
            "tags": [],
            "classTitle": "trophozoite",
            "points": {
                "exterior": [
                    [
                        924,
                        387
                    ],
                    [
                        974,
                        437
                    ]
                ],
                "interior": []
            }
        },
        {
            "id": 98150134,
            "classId": 6509560,
            "description": "",
            "geometryType": "rectangle",
            "labelerLogin": "inbox@datasetninja.com",
            "createdAt": "2023-12-15T16:13:13.854Z",
            "updatedAt": "2023-12-15T16:13:13.854Z",
            "tags": [],
            "classTitle": "trophozoite",
            "points": {
                "exterior": [
                    [
                        586,
                        214
                    ],
                    [
                        636,
                        264
                    ]
                ],
                "interior": []
            }
        },
        {
            "id": 98150133,
            "classId": 6509560,
            "description": "",
            "geometryType": "rectangle",
            "labelerLogin": "inbox@datasetninja.com",
            "createdAt": "2023-12-15T16:13:13.854Z",
            "updatedAt": "2023-12-15T16:13:13.854Z",
            "tags": [],
            "classTitle": "trophozoite",
            "points": {
                "exterior": [
                    [
                        716,
                        239
                    ],
                    [
                        766,
                        289
                    ]
                ],
                "interior": []
            }
        },
        {
            "id": 98150132,
            "classId": 6509560,
            "description": "",
            "geometryType": "rectangle",
            "labelerLogin": "inbox@datasetninja.com",
            "createdAt": "2023-12-15T16:13:13.853Z",
            "updatedAt": "2023-12-15T16:13:13.853Z",
            "tags": [],
            "classTitle": "trophozoite",
            "points": {
                "exterior": [
                    [
                        639,
                        127
                    ],
                    [
                        689,
                        177
                    ]
                ],
                "interior": []
            }
        },
        {
            "id": 98150131,
            "classId": 6509560,
            "description": "",
            "geometryType": "rectangle",
            "labelerLogin": "inbox@datasetninja.com",
            "createdAt": "2023-12-15T16:13:13.853Z",
            "updatedAt": "2023-12-15T16:13:13.853Z",
            "tags": [],
            "classTitle": "trophozoite",
            "points": {
                "exterior": [
                    [
                        706,
                        93
                    ],
                    [
                        756,
                        143
                    ]
                ],
                "interior": []
            }
        },
        {
            "id": 98150130,
            "classId": 6509560,
            "description": "",
            "geometryType": "rectangle",
            "labelerLogin": "inbox@datasetninja.com",
            "createdAt": "2023-12-15T16:13:13.853Z",
            "updatedAt": "2023-12-15T16:13:13.853Z",
            "tags": [],
            "classTitle": "trophozoite",
            "points": {
                "exterior": [
                    [
                        977,
                        146
                    ],
                    [
                        1023,
                        196
                    ]
                ],
                "interior": []
            }
        },
        {
            "id": 98150129,
            "classId": 6509560,
            "description": "",
            "geometryType": "rectangle",
            "labelerLogin": "inbox@datasetninja.com",
            "createdAt": "2023-12-15T16:13:13.853Z",
            "updatedAt": "2023-12-15T16:13:13.853Z",
            "tags": [],
            "classTitle": "trophozoite",
            "points": {
                "exterior": [
                    [
                        970,
                        72
                    ],
                    [
                        1020,
                        122
                    ]
                ],
                "interior": []
            }
        }
    ]
}